magic_cn/__init__.py
magic_cn/gen.py
magic_cn/reg_magic.py
magic_ai_cn-1.0.0.dist-info/LICENSE
magic_ai_cn-1.0.0.dist-info/METADATA
magic_ai_cn-1.0.0.dist-info/WHEEL
magic_ai_cn-1.0.0.dist-info/top_level.txt
magic_ai_cn-1.0.0.dist-info/RECORD
