Metadata-Version: 2.2
Name: magic_ai_cn
Version: 1.0.0
Summary: Esta librería fue creada por IA Sistema de Intres
Home-page: https://www.youtube.com/@IA.Sistema.de.Interes
Author: IA (Sistema de Intres)
Author-email: system.ai.of.interest@gmail.com
License: MIT
Classifier: Programming Language :: Python :: 3
Classifier: Operating System :: OS Independent
Requires-Python: >=3.6
License-File: LICENSE
Requires-Dist: requests
Requires-Dist: tqdm
Requires-Dist: Pillow
Requires-Dist: IPython
Dynamic: author
Dynamic: author-email
Dynamic: classifier
Dynamic: description
Dynamic: description-content-type
Dynamic: home-page
Dynamic: license
Dynamic: requires-dist
Dynamic: requires-python
Dynamic: summary
